dotviewer/__init__.py
dotviewer/__main__.py
dotviewer/dotviewer.py
dotviewer/drawgraph.py
dotviewer/graphclient.py
dotviewer/graphdisplay.py
dotviewer/graphpage.py
dotviewer/graphparse.py
dotviewer/graphserver.py
dotviewer/msgstruct.py
dotviewer/sshgraphserver.py
dotviewer/strunicode.py
dotviewer/font/COPYING.txt
dotviewer/font/DroidSans-Bold.ttf
dotviewer/font/DroidSans.ttf
dotviewer/font/DroidSansMono.ttf
dotviewer/font/FiraMath-Regular.otf
dotviewer/font/LICENSE
dotviewer/font/NotoSans-ExtraLight.ttf
dotviewer/font/NotoSans-Regular.ttf
dotviewer/font/README.txt
dotviewer-0.0.3.dist-info/LICENSE
dotviewer-0.0.3.dist-info/METADATA
dotviewer-0.0.3.dist-info/WHEEL
dotviewer-0.0.3.dist-info/top_level.txt
dotviewer-0.0.3.dist-info/RECORD
