Metadata-Version: 2.1
Name: dotviewer
Version: 0.0.3
Summary: A interactive pygame-based viewer for graphviz files
Home-page: https://foss.heptapod.net/pypy/pypy/-/tree/branch/default/dotviewer
Author: Carl Friedrich Bolz-Tereick
Author-email: cfbolz@gmx.de
License: UNKNOWN
Project-URL: Bug Tracker, https://foss.heptapod.net/pypy/pypy/-/issues
Platform: UNKNOWN
Classifier: Programming Language :: Python
Classifier: License :: OSI Approved :: MIT License
Classifier: Operating System :: OS Independent
Requires-Python: >=3.6
License-File: LICENSE
Requires-Dist: pygame
